setup.py
django_testmaker.egg-info/PKG-INFO
django_testmaker.egg-info/SOURCES.txt
django_testmaker.egg-info/dependency_links.txt
django_testmaker.egg-info/top_level.txt
testmaker/__init__.py
testmaker/management/__init__.py
testmaker/management/commands/__init__.py
testmaker/management/commands/testmaker.py
testmaker/middleware/__init__.py
testmaker/middleware/testmaker.py