Metadata-Version: 1.0
Name: django-testmaker
Version: 0.1
Summary: A package to help automate creation of testing in Django
Home-page: http://code.google.com/p/django-testmaker/
Author: Eric Holscher
Author-email: eric@ericholscher.com
License: UNKNOWN
Platform: UNKNOWN
